{"format_version":"1.10.0","minecraft:client_entity":{"description":{"identifier":"foxy:breakable_barrier","materials":{"default":"foxy_normal"},"textures":{"default":"textures/foxy/entity/barriers","pallet":"textures/foxy/entity/pallet_rack"},"geometry":{"default":"geometry.breakable_barrier"},"scripts":{"pre_animation":["variable.facing = (query.variant) * -90;"],"animate":["direction",{"lower":"query.mark_variant==2 && query.variant==5"},{"death":"!query.is_alive"}]},"animations":{"direction":"animation.foxy_common.face_direction","lower":"animation.breakable_barrier.lower_platform","death":"animation.foxy_common.death_boom"},"particle_effects":{"explosion":"foxy:boom_explosion"},"render_controllers":["controller.render.breakable_barrier"],"spawn_egg":{"base_color":"#f58b00","overlay_color":"#eee3ae"}}}}