{"format_version":"1.10.0","minecraft:client_entity":{"description":{"identifier":"foxy:collectible","materials":{"default":"foxy_normal"},"textures":{"white":"textures/items/dye_powder_white_new","orange":"textures/items/dye_powder_orange","magenta":"textures/items/dye_powder_magenta","light_blue":"textures/items/dye_powder_light_blue","yellow":"textures/items/dye_powder_yellow","lime":"textures/items/dye_powder_lime","pink":"textures/items/dye_powder_pink","gray":"textures/items/dye_powder_gray","silver":"textures/items/dye_powder_silver","cyan":"textures/items/dye_powder_cyan","purple":"textures/items/dye_powder_purple","blue":"textures/items/dye_powder_blue_new","brown":"textures/items/dye_powder_brown_new","green":"textures/items/dye_powder_green","red":"textures/items/dye_powder_red","black":"textures/items/dye_powder_black_new","default":"textures/blocks/beehive_front","seventeen":"textures/items/clay_ball"},"geometry":{"default":"geometry.collectible"},"scripts":{"animate":["spin","hover"]},"animations":{"spin":"animation.foxy_common.idle_spin","hover":"animation.foxy_common.idle_hover"},"render_controllers":["controller.render.foxy_pseudocolored"],"spawn_egg":{"base_color":"#F3EC18","overlay_color":"#F47621"}}}}