{"format_version":"1.10.0","minecraft:client_entity":{"description":{"identifier":"foxy:lost_kitten","materials":{"glow":"foxy_colored","outline":"foxy_spectral_front_outline"},"textures":{"glow":"textures/entity/cat/allblackcat_tame","outline":"textures/foxy/entity/black"},"geometry":{"glow":"geometry.foxy_cat","outline":"geometry.foxy_cat.outline"},"scripts":{"animate":["sit","look_at_target","baby_transform"]},"animations":{"sit":"animation.cat.sit","look_at_target":"animation.common.look_at_target","baby_transform":"animation.cat.baby_transform"},"render_controllers":["controller.render.foxy_normal.outline","controller.render.foxy_glow"],"spawn_egg":{"texture":"spawn_egg_boom_lost_kitten","texture_index":0}}}}